event_processor/__init__.py
event_processor/dependencies.py
event_processor/error_handling_strategies.py
event_processor/event_processor.py
event_processor/exceptions.py
event_processor/filters.py
event_processor/invocation_strategies.py
event_processor/py.typed
event_processor/result.py
event_processor/util.py
tests/__init__.py
tests/test_dependencies.py
tests/test_end_to_end.py
tests/test_error_handling_strategies.py
tests/test_event_processor.py
tests/test_filters.py
tests/test_invocation_strategies.py
tests/test_result.py
tests/test_util.py
tests/package_for_tests/__init__.py
tests/package_for_tests/a_module.py
tests/package_for_tests/b_module.py
event_processor-3.2.1.dist-info/LICENSE
event_processor-3.2.1.dist-info/METADATA
event_processor-3.2.1.dist-info/WHEEL
event_processor-3.2.1.dist-info/top_level.txt
event_processor-3.2.1.dist-info/zip-safe
event_processor-3.2.1.dist-info/RECORD
