Metadata-Version: 2.1
Name: event-processor
Version: 3.2.1
Summary: Pythonic event-processing library based on decorators
Home-page: https://github.com/marier-nico/event-processor
Author: Nicolas Marier
Author-email: software@nmarier.com
License: UNKNOWN
Project-URL: Documentation, https://event-processor.readthedocs.io/en/latest/
Project-URL: Source, https://github.com/marier-nico/event-processor
Project-URL: Tracker, https://github.com/marier-nico/event-processor/issues
Keywords: event decorators development
Platform: any
Classifier: Development Status :: 4 - Beta
Classifier: Intended Audience :: Developers
Classifier: License :: OSI Approved :: MIT License
Classifier: Topic :: Software Development :: Libraries
Classifier: Programming Language :: Python :: 3.7
Classifier: Programming Language :: Python :: 3.8
Classifier: Programming Language :: Python :: 3.9
Classifier: Programming Language :: Python :: 3.10
Classifier: Programming Language :: Python :: 3.11
License-File: LICENSE
Provides-Extra: pydantic
Requires-Dist: pydantic (<3.0,>=1.8.2) ; extra == 'pydantic'
